CriadorDeCortes/__init_.py
CriadorDeCortes/podcast.py
CriadorDeCortes-0.0.6.dist-info/METADATA
CriadorDeCortes-0.0.6.dist-info/WHEEL
CriadorDeCortes-0.0.6.dist-info/top_level.txt
CriadorDeCortes-0.0.6.dist-info/RECORD
