Metadata-Version: 2.1
Name: CriadorDeCortes
Version: 0.0.6
Summary: Para você que deseja farmar dinheiro com conteúdo de terceiros sem precisar ter esforço algum
Home-page: https://github.com/leozamboni/GeradorDeCortes
Author: Leonardo Zamboni
Author-email: leonardonunes169@gmail.com
License: UNKNOWN
Project-URL: Bug Tracker, https://github.com/leozamboni/GeradorDeCortes/issues
Platform: UNKNOWN
Classifier: Programming Language :: Python :: 3
Classifier: License :: OSI Approved :: MIT License
Classifier: Operating System :: OS Independent
Requires-Python: >=3.6
Requires-Dist: pytube3
Requires-Dist: SpeechRecognition
Requires-Dist: moviepy
